scine_kinetx/LICENSE.txt
scine_kinetx/__init__.py
scine_kinetx/scine_kinetx.cpython-310-x86_64-linux-gnu.so
scine_kinetx.libs/libgomp-e985bcbb.so.1.0.0
scine_kinetx.libs/libkinetx-3c527610.so
scine_kinetx.libs/libsundials_cvode-b0465694.so.6.7.0
scine_kinetx.libs/libsundials_nvecopenmp-0d938ec5.so.6.7.0
scine_kinetx.libs/libsundials_sunmatrixdense-93e841fd.so.4.7.0
scine_kinetx.libs/libsundials_sunmatrixsparse-951903ec.so.4.7.0
scine_kinetx.libs/libsundials_sunnonlinsolfixedpoint-a8abaac2.so.3.7.0
scine_kinetx.libs/libsundials_sunnonlinsolnewton-cb8d3ce9.so.3.7.0
scine_kinetx-3.1.0.dist-info/METADATA
scine_kinetx-3.1.0.dist-info/WHEEL
scine_kinetx-3.1.0.dist-info/top_level.txt
scine_kinetx-3.1.0.dist-info/RECORD
