Metadata-Version: 2.1
Name: scine_kinetx
Version: 3.1.0
Summary: Kinetic Modelling of Reaction Networks
Home-page: https://www.scine.ethz.ch
Author: ETH Zurich, Department of Chemistry and Applied Biosciences, Reiher Group
Author-email: scine@phys.chem.ethz.ch
Classifier: Programming Language :: Python
Classifier: Programming Language :: C++
Classifier: Development Status :: 5 - Production/Stable
Classifier: Intended Audience :: Science/Research
Classifier: License :: OSI Approved :: BSD License
Classifier: Natural Language :: English
Classifier: Topic :: Scientific/Engineering :: Chemistry
Requires-Dist: numpy
Requires-Dist: scipy
